README.md
setup.py
DYGI/DYGIt.py
DYGIt.egg-info/PKG-INFO
DYGIt.egg-info/SOURCES.txt
DYGIt.egg-info/dependency_links.txt
DYGIt.egg-info/requires.txt
DYGIt.egg-info/top_level.txt