Metadata-Version: 2.1
Name: DYGIt
Version: 6.0
Summary: A text based email client for those of us without a UI.
Home-page: https://github.com/myson1515/DYGI
Author: Mason Lapine
Author-email: masonlapine@gmail.com
License: MIT
Platform: UNKNOWN
